[{"children":[{"children":[{"dateAdded":1564710246891,"id":"68","index":0,"parentId":"56","title":"百度","url":"https://www.baidu.com/?bn=centbrowser"},{"dateAdded":1564710246895,"id":"69","index":1,"parentId":"56","title":"网易","url":"http://www.163.com/"},{"dateAdded":1564710246895,"id":"70","index":2,"parentId":"56","title":"微博","url":"https://weibo.com/"},{"dateAdded":1564710246895,"id":"71","index":3,"parentId":"56","title":"知乎","url":"https://www.zhihu.com/"},{"dateAdded":1564710246895,"id":"72","index":4,"parentId":"56","title":"哔哩哔哩","url":"https://www.bilibili.com/"},{"dateAdded":1564710246895,"id":"73","index":5,"parentId":"56","title":"优酷","url":"https://www.youku.com/"},{"dateAdded":1564710246895,"id":"74","index":6,"parentId":"56","title":"爱奇艺","url":"http://www.iqiyi.com/"},{"dateAdded":1564710246896,"id":"75","index":7,"parentId":"56","title":"凤凰网","url":"http://www.ifeng.com/"},{"dateAdded":1564710246896,"id":"76","index":8,"parentId":"56","title":"百度地图","url":"https://map.baidu.com/"},{"dateAdded":1564710246896,"id":"77","index":9,"parentId":"56","title":"网易云音乐","url":"https://music.163.com/"},{"dateAdded":1564710246896,"id":"78","index":10,"parentId":"56","title":"斗鱼直播","url":"https://www.douyu.com/"},{"dateAdded":1564710246896,"id":"79","index":11,"parentId":"56","title":"虎牙直播","url":"https://www.huya.com/"},{"dateAdded":1564710246896,"id":"80","index":12,"parentId":"56","title":"花椒直播","url":"http://www.huajiao.com/"},{"dateAdded":1564710246896,"id":"81","index":13,"parentId":"56","title":"58同城","url":"http://www.58.com/"},{"dateAdded":1564710246896,"id":"82","index":14,"parentId":"56","title":"汽车之家","url":"https://www.autohome.com.cn/"},{"dateAdded":1564710246896,"id":"83","index":15,"parentId":"56","title":"中国铁路12306","url":"https://www.12306.cn/"},{"dateAdded":1564710246896,"id":"84","index":16,"parentId":"56","title":"金山词霸在线","url":"http://www.iciba.com/"},{"dateAdded":1564710246896,"id":"85","index":17,"parentId":"56","title":"IP138查询网","url":"http://qq.ip138.com/day/"}],"dateAdded":1564710246854,"dateGroupModified":1564710246896,"id":"56","index":0,"parentId":"1","title":"常用网址"},{"children":[{"dateAdded":1564710246896,"id":"86","index":0,"parentId":"57","title":"京东商城","url":"https://union-click.jd.com/jdc?e=0&p=AyIPZRprFDJWWA1FBCVbV0IUWVALHFRBEwQAQB1AWQkrPUZEVQEVYx51XUp4XUVdTUYUY1RaHRkOfARUG10JAxQbVR5KFAIZA1cQWRwyGwBUHVkTCxMEZRtaFAMRAF0dXR0yIgdUKxB7AyIPVR5bEQQUAlcrWxAKGg9SEl4VCxUHXCtcJX1MWQBGDxYDEgRlK2sl&t=W1dCFFlQCxxUQRMEAEAdQFkJ"},{"dateAdded":1564710246901,"id":"87","index":1,"parentId":"57","title":"天猫","url":"https://s.click.taobao.com/t?e=m%3D2%26s%3Dfw9yP4v9odYcQipKwQzePCperVdZeJvipRe%2F8jaAHci5VBFTL4hn2aULgaWcFwpSNMWYSf9G9hF1gQExDICj1TthLh543o4VognO5oc0hzE%2FQDTcEjS7z%2BTEWJdP8jmRm5UnbMkTZzQAIWlNq522QRoeSzb988W7cSpj5qSCmbA%3D"},{"dateAdded":1564710246901,"id":"88","index":2,"parentId":"57","title":"天猫超市","url":"https://s.click.taobao.com/t?e=m%3D2%26s%3DtSX7U%2BKYAcscQipKwQzePCperVdZeJviK7Vc7tFgwiFRAdhuF14FMVuSRdvCUUla1aH1Hk3GeOiKYGETRd6WgfZeR4k6D3Z64IfWFYv9x3VuHmHPm0pLT44nZdlWtg%2FJuH1hWG3%2BVYSM%2BhtH71aX6qobGvjZ2M66sjgPXEs9keN%2BPGXoAieI2tfEJZuu2RKIjk3u7s1M%2Bek5hDCuE8TSLA%3D%3D"},{"dateAdded":1564710246901,"id":"89","index":3,"parentId":"57","title":"网易考拉海购","url":"https://www.kaola.com/"},{"dateAdded":1564710246901,"id":"90","index":4,"parentId":"57","title":"购优惠（淘宝内部优惠券）","url":"https://www.quan82.com/"},{"dateAdded":1564710246901,"id":"91","index":5,"parentId":"57","title":"N淘网（淘宝内部优惠券）","url":"https://www.ntaow.com/"},{"dateAdded":1564710246902,"id":"92","index":6,"parentId":"57","title":"亚马逊中国","url":"https://www.amazon.cn/"},{"dateAdded":1564710246902,"id":"93","index":7,"parentId":"57","title":"唯品会","url":"https://click.union.vip.com/redirect.php?code=Cpj9Gg8"},{"dateAdded":1564710246902,"id":"94","index":8,"parentId":"57","title":"苏宁易购","url":"https://www.suning.com/"},{"dateAdded":1564710246902,"id":"95","index":9,"parentId":"57","title":"国美在线","url":"https://www.gome.com.cn/"},{"dateAdded":1564710246902,"id":"96","index":10,"parentId":"57","title":"携程旅行网","url":"http://u.ctrip.com/union/CtripRedirect.aspx?TypeID=2&Allianceid=765853&sid=1311987&OUID=&jumpUrl=http%3A%2F%2Fwww.ctrip.com%2F%3FAllianceid%3D765853%26sid%3D1311987%26OUID%3D%26MultiUnionSupport%3Dtrue"},{"dateAdded":1564710246903,"id":"97","index":11,"parentId":"57","title":"去哪儿网","url":"https://www.qunar.com/"}],"dateAdded":1564710246855,"dateGroupModified":1564710246903,"id":"57","index":1,"parentId":"1","title":"网上购物"},{"dateAdded":1564710246856,"id":"58","index":2,"parentId":"1","title":"导入书签","url":"chrome://settings/importData"},{"dateAdded":1564710246856,"id":"59","index":3,"parentId":"1","title":"《⑨也懂系列：MinGW安装教程Ver.2》著名C/C++编译器GCC的Windows版本 | rsreland","url":"http://rsreland.net/archives/344"},{"dateAdded":1564710246857,"id":"60","index":4,"parentId":"1","title":"工时统计 -","url":"http://10.8.200.161:9527/#/dashboard"},{"dateAdded":1564710246858,"id":"61","index":5,"parentId":"1","title":"Qt里的原子操作QAtomicInteger - findumars - 博客园","url":"https://www.cnblogs.com/findumars/p/10247181.html"},{"dateAdded":1564710246859,"id":"62","index":6,"parentId":"1","title":"我的地盘 - 禅道","url":"http://10.8.200.180:8080/zentao/my/"},{"dateAdded":1564710246860,"id":"63","index":7,"parentId":"1","title":"碧桂园统一认证服务","url":"https://login.countrygarden.com.cn/idp/authcenter/ActionAuthChain?entityId=bip"},{"dateAdded":1564710246860,"id":"64","index":8,"parentId":"1","title":"Projects · Dashboard · GitLab","url":"http://10.8.200.161/"},{"dateAdded":1564710246861,"id":"65","index":9,"parentId":"1","title":"draw.io","url":"https://www.draw.io/"},{"dateAdded":1564710246863,"id":"66","index":10,"parentId":"1","title":"Software Engineering Department / Differential Wheeled and Light Load AGV Team / AGVs Traffic Control · GitLab","url":"http://10.8.200.161/softwareengineering/material-handling-robot-team/agvs-traffic-control"},{"dateAdded":1564710246864,"id":"67","index":11,"parentId":"1","title":"Guice 快速入门 - cnhome的专栏 - CSDN博客","url":"https://blog.csdn.net/cnhome/article/details/80627123"}],"dateAdded":1559522610631,"dateGroupModified":1564710246864,"id":"1","index":0,"parentId":"0","title":"书签栏"}]